[
    {
        "Judul Lowongan": "INTERNSHIP 2026 - PT Pertamina (Persero) - Fungsi Corporate Secretary (Government Relations)",
        "Perusahaan": "PT Pertamina",
        "Kota": "Tidak tertera",
        "Industri": "Tidak tertera",
        "Sektor": "Energy",
        "Pendidikan": "Tidak tertera",
        "Jurusan": "Semua Jurusan / Tidak tertera",
        "Kuota": 1,
        "Pelamar": 154,
        "Link Detail": "https://recruitment.pertamina.com/object/widget/845abfe1-3f9d-4b3a-bda5-0a9f2f9083c2/?id=7a5566ac-8ae0-41da-a272-6aeccc6b2cc3"
    },
    {
        "Judul Lowongan": "INTERNSHIP 2026 - PT Pertamina Patra Niaga - Risk RJBT",
        "Perusahaan": "PT Pertamina",
        "Kota": "Tidak tertera",
        "Industri": "Tidak tertera",
        "Sektor": "Energy",
        "Pendidikan": "Tidak tertera",
        "Jurusan": "Semua Jurusan / Tidak tertera",
        "Kuota": 1,
        "Pelamar": 202,
        "Link Detail": "https://recruitment.pertamina.com/object/widget/845abfe1-3f9d-4b3a-bda5-0a9f2f9083c2/?id=f1f3d324-81b6-42b6-a750-33d1d88a2652"
    },
    {
        "Judul Lowongan": "INTERNSHIP 2026 - PT Pertamina Gas - Fungsi HC Policy & BP",
        "Perusahaan": "PT Pertamina",
        "Kota": "Tidak tertera",
        "Industri": "Tidak tertera",
        "Sektor": "Energy",
        "Pendidikan": "Tidak tertera",
        "Jurusan": "Semua Jurusan / Tidak tertera",
        "Kuota": 2,
        "Pelamar": 461,
        "Link Detail": "https://recruitment.pertamina.com/object/widget/845abfe1-3f9d-4b3a-bda5-0a9f2f9083c2/?id=d6904977-1f29-4786-b229-345ef9f6b82b"
    },
    {
        "Judul Lowongan": "INTERNSHIP 2026 - PT Gagas Energi Indonesia - Fungsi IT Development",
        "Perusahaan": "PT Pertamina",
        "Kota": "Tidak tertera",
        "Industri": "Tidak tertera",
        "Sektor": "Energy",
        "Pendidikan": "Tidak tertera",
        "Jurusan": "Semua Jurusan / Tidak tertera",
        "Kuota": 1,
        "Pelamar": 872,
        "Link Detail": "https://recruitment.pertamina.com/object/widget/845abfe1-3f9d-4b3a-bda5-0a9f2f9083c2/?id=4ae7e45d-06c7-4c70-8ae5-3480d29a2552"
    }
]